wde/__init__.py
wde/config.py
wde/constants.py
wde/container.py
wde/main.py
wde/utils.py
wde/cli/__init__.py
wde/cli/base.py
wde/cli/database.py
wde/cli/docker.py
wde/cli/install.py
wde/cli/website.py
wde-0.2.0.dist-info/METADATA
wde-0.2.0.dist-info/WHEEL
wde-0.2.0.dist-info/entry_points.txt
wde-0.2.0.dist-info/top_level.txt
wde-0.2.0.dist-info/RECORD
