Metadata-Version: 2.1
Name: wde
Version: 0.2.0
Summary: WebDevEnv Tools
Home-page: UNKNOWN
Author: Egor Dmitriev
Author-email: egordmitriev2@gmail.com
License: UNKNOWN
Platform: UNKNOWN
Classifier: Programming Language :: Python :: 3
Classifier: Operating System :: OS Independent
Requires-Python: >=3.5
